TrimPypi/__init__.py
TrimPypi/main.py
TrimPypi-0.0.2.dist-info/LICENSE
TrimPypi-0.0.2.dist-info/METADATA
TrimPypi-0.0.2.dist-info/WHEEL
TrimPypi-0.0.2.dist-info/top_level.txt
TrimPypi-0.0.2.dist-info/RECORD
